php_version_compare/__init__.py
php_version_compare/versioning.py
php_version_compare-1.1.2.dist-info/METADATA
php_version_compare-1.1.2.dist-info/WHEEL
php_version_compare-1.1.2.dist-info/licenses/LICENSE-APACHE
php_version_compare-1.1.2.dist-info/licenses/LICENSE-MIT
php_version_compare-1.1.2.dist-info/RECORD
