Metadata-Version: 2.3
Name: php-version-compare
Version: 1.1.2
Summary: PHP-compatible version comparison for Python
Project-URL: Documentation, https://php-version-compare.readthedocs.io
Project-URL: Repository, https://github.com/marcfrederick/php-version-compare
Project-URL: Issues, https://github.com/marcfrederick/php-version-compare/issues
Project-URL: Changelog, https://github.com/marcfrederick/php-version-compare/releases
Author-email: Marc Trölitzsch <marc.troelitzsch@gmail.com>
License-File: LICENSE-APACHE
License-File: LICENSE-MIT
Keywords: compare,comparison,compatibility,php,version
Classifier: Development Status :: 5 - Production/Stable
Classifier: Intended Audience :: Developers
Classifier: License :: OSI Approved :: Apache Software License
Classifier: License :: OSI Approved :: MIT License
Classifier: Programming Language :: Python :: 3
Classifier: Programming Language :: Python :: 3 :: Only
Classifier: Programming Language :: Python :: 3.6
Classifier: Programming Language :: Python :: 3.7
Classifier: Programming Language :: Python :: 3.8
Classifier: Programming Language :: Python :: 3.9
Classifier: Programming Language :: Python :: 3.10
Classifier: Programming Language :: Python :: 3.11
Classifier: Programming Language :: Python :: 3.12
Classifier: Programming Language :: Python :: 3.13
Classifier: Programming Language :: Python :: 3.14
Classifier: Topic :: Software Development :: Libraries
Classifier: Topic :: Software Development :: Libraries :: Python Modules
Requires-Python: >=3.6
Requires-Dist: typing-extensions; python_version < '3.8'
Provides-Extra: dev
Requires-Dist: bump-my-version; extra == 'dev'
Requires-Dist: hatchling; extra == 'dev'
Requires-Dist: ruff; extra == 'dev'
Requires-Dist: tox; extra == 'dev'
Provides-Extra: docs
Requires-Dist: sphinx; extra == 'docs'
Requires-Dist: sphinx-rtd-theme; extra == 'docs'
Provides-Extra: test
Requires-Dist: pytest; extra == 'test'
Requires-Dist: pytest-cov; extra == 'test'
Requires-Dist: pytest-randomly; extra == 'test'
